agrometeo/__init__.py
agrometeo/base.py
agrometeo/core.py
agrometeo/plotting.py
agrometeo/settings.py
agrometeo_geopy-0.2.0.dist-info/LICENSE
agrometeo_geopy-0.2.0.dist-info/METADATA
agrometeo_geopy-0.2.0.dist-info/WHEEL
agrometeo_geopy-0.2.0.dist-info/top_level.txt
agrometeo_geopy-0.2.0.dist-info/RECORD
