Metadata-Version: 2.1
Name: agrometeo-geopy
Version: 0.2.0
Summary: Pythonic interface to access Agrometeo data.
Author-email: Martí Bosch <marti.bosch@protonmail.com>
License: GPL-3.0-only
Project-URL: Repository, https://github.com/martibosch/agrometeo-geopy
Classifier: Development Status :: 2 - Pre-Alpha
Classifier: Intended Audience :: Developers
Classifier: License :: OSI Approved :: GNU General Public License v3 (GPLv3)
Classifier: Natural Language :: English
Classifier: Programming Language :: Python :: 3
Classifier: Programming Language :: Python :: 3.8
Classifier: Programming Language :: Python :: 3.9
Classifier: Programming Language :: Python :: 3.10
Classifier: Programming Language :: Python :: 3.11
Requires-Python: >=3.8
License-File: LICENSE
Requires-Dist: geopandas (>=0.8.0)
Requires-Dist: matplotlib
Requires-Dist: requests
Provides-Extra: cx
Requires-Dist: contextily ; extra == 'cx'
Provides-Extra: dev
Requires-Dist: build ; extra == 'dev'
Requires-Dist: bump2version ; extra == 'dev'
Requires-Dist: pre-commit ; extra == 'dev'
Requires-Dist: pip ; extra == 'dev'
Requires-Dist: toml ; extra == 'dev'
Requires-Dist: tox ; extra == 'dev'
Requires-Dist: twine ; extra == 'dev'
Provides-Extra: doc
Requires-Dist: myst-parser ; extra == 'doc'
Requires-Dist: nbsphinx ; extra == 'doc'
Requires-Dist: sphinx ; extra == 'doc'
Provides-Extra: ox
Requires-Dist: osmnx ; extra == 'ox'
Provides-Extra: test
Requires-Dist: black ; extra == 'test'
Requires-Dist: coverage[toml] ; extra == 'test'
Requires-Dist: pytest ; extra == 'test'
Requires-Dist: pytest-cov ; extra == 'test'
Requires-Dist: ruff ; extra == 'test'
